README.md
setup.cfg
setup.py
distr_probab/Binomialdistribution.py
distr_probab/Gaussiandistribution.py
distr_probab/Generaldistribution.py
distr_probab/__init__.py
distr_probab.egg-info/PKG-INFO
distr_probab.egg-info/SOURCES.txt
distr_probab.egg-info/dependency_links.txt
distr_probab.egg-info/not-zip-safe
distr_probab.egg-info/top_level.txt