Metadata-Version: 1.0
Name: distr-probab
Version: 0.2
Summary: Gaussian and Binomial distributions
Home-page: UNKNOWN
Author: Sagar Das
Author-email: sagarrdass@gmail.com
License: UNKNOWN
Platform: UNKNOWN
